certbot_dns_timeweb/__init__.py
certbot_dns_timeweb/authenticator.py
certbot_dns_timeweb-1.0.1.dist-info/LICENSE
certbot_dns_timeweb-1.0.1.dist-info/METADATA
certbot_dns_timeweb-1.0.1.dist-info/WHEEL
certbot_dns_timeweb-1.0.1.dist-info/entry_points.txt
certbot_dns_timeweb-1.0.1.dist-info/RECORD
