Metadata-Version: 2.1
Name: certbot-dns-timeweb
Version: 1.0.1
Summary: Timeweb DNS Authenticator plugin for Certbot
License: MIT
Author: Aleksandr Ivanov
Author-email: oz.sasha.ivanov@gmail.com
Requires-Python: >=3.10,<4.0
Classifier: License :: OSI Approved :: MIT License
Classifier: Programming Language :: Python :: 3
Classifier: Programming Language :: Python :: 3.10
Classifier: Programming Language :: Python :: 3.11
Classifier: Programming Language :: Python :: 3.12
Requires-Dist: certbot (>=2.8,<3.0)
Requires-Dist: timeweb-cloud (>=0.12.2,<0.13.0)
Requires-Dist: tld (>=0.13,<0.14)
